infinstor_py_bootstrap.pth
infinstor_py_bootstrap/__init__.py
infinstor_py_bootstrap/infinstor_py_bootstrap.py
infinstor_py_bootstrap/pip_dry_run.py
infinstor_py_bootstrap-1.0.3.dist-info/METADATA
infinstor_py_bootstrap-1.0.3.dist-info/WHEEL
infinstor_py_bootstrap-1.0.3.dist-info/top_level.txt
infinstor_py_bootstrap-1.0.3.dist-info/RECORD
