Metadata-Version: 2.1
Name: infinstor-py-bootstrap
Version: 1.0.3
Summary: InfinStor Python Packages Bootstrapper
Home-page: UNKNOWN
Author: InfinStor, Inc.
Author-email: support@infinstor.com
License: AGPL-3.0
Keywords: Jupyter,JupyterLab,InfinStor,InfinSnap,InfinSlice
Platform: Linux
Platform: Mac OS X
Platform: Windows
Classifier: Intended Audience :: Developers
Classifier: Intended Audience :: Education
Classifier: Intended Audience :: Science/Research
Classifier: License :: OSI Approved :: GNU Affero General Public License v3 or later (AGPLv3+)
Classifier: Programming Language :: Python
Classifier: Programming Language :: Python :: 3
Requires-Python: >=3.5
Requires-Dist: jsons
Requires-Dist: filelock
Requires-Dist: psutil
